__init__.py
clock.py
configuration.py
data.py
guanaco.py
guanaco_trade-0.1.0.dist-info/LICENSE.txt
guanaco_trade-0.1.0.dist-info/METADATA
guanaco_trade-0.1.0.dist-info/WHEEL
guanaco_trade-0.1.0.dist-info/top_level.txt
guanaco_trade-0.1.0.dist-info/RECORD
