Metadata-Version: 2.1
Name: guanaco-trade
Version: 0.1.0
Summary: A stock trading tool that utilizes generative AI.
Author-email: Ben Boonstra <bboonstra@gmail.com>
Maintainer-email: Ben Boonstra <bboonstra@gmail.com>
License: MIT License
Project-URL: Homepage, https://github.com/IceFire03/guanaco-trade
Project-URL: Issues, https://github.com/IceFire03/guanaco-trade/issues
Classifier: Programming Language :: Python :: 3
Classifier: License :: OSI Approved :: MIT License
Classifier: Operating System :: OS Independent
Requires-Python: >=3.12
License-File: LICENSE.txt
